{
    "title":  "Temida w algorytmicznym zwierciadle: Czy sztuczna inteligencja zrewolucjonizuje sprawiedliwość?",
    "topic":  "AI w sądownictwie",
    "excerpt":  "W dobie rosnącej potęgi sztucznej inteligencji, pojawia się fascynujące pytanie: czy algorytmy mogą być bardziej sprawiedliwe niż ludzki sędzia? Zanurzmy się w świat, gdzie technologia spotyka się z Temidą, by odkryć jej potencjał i ograniczenia.",
    "date":  "1 czerwca 2026",
    "html":  "\u003ch2\u003eWstęp: Algorytmy na sali sądowej – wizja przyszłości?\u003c/h2\u003e\u003cp\u003eWyobraźmy sobie świat, w którym sprawiedliwość wymierzana jest z bezbłędną precyzją, wolna od ludzkich emocji, uprzedzeń i zmęczenia. Wizja ta, jeszcze niedawno domeną science fiction, coraz śmielej puka do drzwi wymiaru sprawiedliwości za sprawą sztucznej inteligencji (AI). Czy maszyna, pozbawiona subiektywnych odczuć, może być bardziej sprawiedliwa niż człowiek w todze? To pytanie rezonuje w dyskusjach ekspertów na całym świecie, otwierając fascynującą debatę o przyszłości prawa i roli człowieka w jego stosowaniu.\u003c/p\u003e\u003ch2\u003eObietnica efektywności i szybkości\u003c/h2\u003e\u003cp\u003eJednym z najbardziej oczywistych i już realizowanych zastosowań AI w sądownictwie jest usprawnienie procesów administracyjnych i analitycznych. Sztuczna inteligencja potrafi w mgnieniu oka analizować ogromne zbiory danych, wyszukiwać orzecznictwo, monitorować zmiany w aktach prawnych, a nawet transkrybować przebieg rozpraw. Dzięki temu sędziowie mogą zostać odciążeni od czasochłonnych, powtarzalnych zadań, zyskując więcej czasu na merytoryczne aspekty spraw.\u003c/p\u003e\u003cblockquote\u003e„W polskich sądach sztuczna inteligencja jest już wykorzystywana w prostych zadaniach, takich jak anonimizacja dokumentów, transkrypcja, wyszukiwanie orzeczeń czy chociażby monitorowanie i śledzenie zmian aktów prawnych.”\u003c/blockquote\u003e\u003cp\u003eSystemy AI mogą również dokonywać wstępnej selekcji dokumentów, sprawdzać braki formalne pozwów czy identyfikować klauzule abuzywne w umowach, co znacząco przyspiesza przepływ pracy w sądach. Co więcej, w niektórych jurysdykcjach, takich jak Chiny, „inteligentne sądy” wykorzystują AI do automatyzacji zarządzania sprawami i analizy dowodów, zwłaszcza w sprawach rutynowych i masowych. Nawet w Polsce sędziowie eksperymentują z modelami AI do dodatkowych wyliczeń, nie zastępując jednak opinii biegłych.\u003c/p\u003e\u003ch2\u003eDążenie do bezstronności – iluzja czy realna szansa?\u003c/h2\u003e\u003cp\u003eArgumentem często wysuwanym na korzyść algorytmów jest ich potencjalna bezstronność. Maszyna nie ulega zmęczeniu, nie ma osobistych uprzedzeń ani emocji, które mogłyby wpłynąć na jej decyzje. W teorii, algorytm, opierając się wyłącznie na faktach i przepisach, mógłby wydawać bardziej konsekwentne i jednolite wyroki, zwiększając stabilność orzecznictwa. To z kolei mogłoby prowadzić do większego zaufania do systemu sprawiedliwości. Jednak rzeczywistość jest bardziej złożona. Algorytmy uczą się na podstawie danych historycznych, które same w sobie mogą zawierać zakodowane uprzedzenia społeczne. Jeśli dane wejściowe są obciążone stronniczością, algorytm będzie ją powielał, a nawet wzmacniał, prowadząc do niesprawiedliwych rozstrzygnięć.\u003c/p\u003e\u003ch2\u003eNiezastąpiony czynnik ludzki: Emocje, kontekst i „trudne przypadki”\u003c/h2\u003e\u003cp\u003eMimo imponujących możliwości AI, panuje powszechne przekonanie, że sztuczna inteligencja nie zastąpi sędziego. Kluczową różnicą jest zdolność człowieka do interpretacji prawa w kontekście konkretnej sytuacji życiowej, do ważenia racji, oceny motywów działania oraz rozumienia niestandardowych okoliczności. Prawo to nie matematyka, a sprawiedliwość to nie wyłącznie problem obliczeniowy.\u003c/p\u003e\u003cblockquote\u003e„AI nie zna litości, winy ani kontekstu społecznego. Jej rola kończy się tam, gdzie zaczyna się prawdziwie sądowa władza: odpowiedzialna, refleksyjna, ludzka.”\u003c/blockquote\u003e\u003cp\u003eProfesorowie prawa podkreślają, że sędziowie muszą radzić sobie z tzw. „hard cases” – sprawami trudnymi, w których konieczne jest odejście od dotychczasowej linii orzeczniczej ze względu na zmiany cywilizacyjne czy nowe zagrożenia. Takie decyzje wymagają empatii, moralnej intuicji i życiowego doświadczenia, których algorytmy nie posiadają. Dodatkowo, w wielu krajach, w tym w Polsce, konstytucja jasno stanowi, że wyroki wydawać mogą wyłącznie sędziowie będący ludźmi, a zmiana tego zapisu spotkałaby się z silnym sprzeciwem społecznym. Zaufanie do wymiaru sprawiedliwości opiera się na interakcji z ludźmi, a nie z maszynami.\u003c/p\u003e\u003ch2\u003eWyzwania i ryzyka: Od halucynacji po kwestie etyczne\u003c/h2\u003e\u003cp\u003eWdrożenie AI w sądownictwie wiąże się również z szeregiem poważnych wyzwań. Jednym z nich jest tzw. „problem czarnej skrzynki”, czyli brak przejrzystości w działaniu algorytmów, co utrudnia zrozumienie, w jaki sposób AI dochodzi do swoich wniosków. To z kolei podważa zasadę prawa do rzetelnego procesu. Istnieje także ryzyko „halucynacji” modeli AI, czyli generowania nieistniejących przepisów prawnych, wyroków czy literatury, co może prowadzić do poważnych błędów. Odpowiedzialność za te błędy nadal spoczywa na osobie korzystającej z AI.\u003c/p\u003e\u003cp\u003eUnijne rozporządzenie AI Act klasyfikuje rozwiązania sztucznej inteligencji w wymiarze sprawiedliwości jako kategorię wysokiego ryzyka, co oznacza konieczność wdrożenia procedur nadzoru nad algorytmami. Wymaga to od sędziów i prawników posiadania kompetencji w zakresie wykorzystywanych technologii oraz umiejętności weryfikacji treści generowanych przez AI. W Polsce dodatkową barierą jest niski poziom cyfryzacji postępowania cywilnego, co uniemożliwia efektywne wykorzystanie sztucznej inteligencji, która potrzebuje dostępu do danych elektronicznych.\u003c/p\u003e\u003ch2\u003ePrzyszłość: AI jako potężny asystent, nie sędzia\u003c/h2\u003e\u003cp\u003eKonsensus wśród ekspertów jest jasny: sztuczna inteligencja ma ogromny potencjał, by stać się niezwykle cennym asystentem sędziego, rewolucjonizującym pracę sądów i kancelarii prawnych. Może pomóc w prowadzeniu akt, wyszukiwaniu dowodów, proponowaniu podstaw prawnych, a nawet w przygotowywaniu treści orzeczeń na podstawie podobnych spraw. Prawnicy coraz częściej korzystają z generatywnej AI do researchu, analizy i automatyzacji tworzenia dokumentów.\u003c/p\u003e\u003cp\u003eJednakże, rola AI w sądownictwie powinna być zawsze pomocnicza i doradcza. Ostateczna decyzja musi pozostać w rękach człowieka, który jest w stanie wziąć pod uwagę złożoność ludzkich doświadczeń, moralne dylematy i zmieniający się kontekst społeczny. Rozwój AI wymaga ciągłej dyskusji, analizy i wypracowywania ram prawnych i etycznych, aby zapewnić, że technologia służy sprawiedliwości, a nie ją wypacza.\u003c/p\u003e\u003ch2\u003eZakończenie: Sprawiedliwość z ludzką twarzą, wspomagana przez technologię\u003c/h2\u003e\u003cp\u003ePytanie, czy algorytm może być bardziej sprawiedliwy niż sędzia, prowadzi nas do refleksji nad samą naturą sprawiedliwości. Choć AI oferuje obietnicę obiektywności i efektywności, to właśnie ludzka zdolność do empatii, zrozumienia niuansów i podejmowania trudnych decyzji w oparciu o wartości etyczne pozostaje niezastąpiona. Sztuczna inteligencja nie jest zagrożeniem dla Temidy, lecz raczej potężnym narzędziem, które, odpowiednio wykorzystane i nadzorowane, może pomóc jej lśnić jaśniej. Przyszłość wymiaru sprawiedliwości to symbioza – sprawiedliwość z ludzką twarzą, inteligentnie wspomagana przez algorytmy.\u003c/p\u003e",
    "imageUrl":  "posts/images/temida-w-algorytmicznym-zwierciadle-czy-sztuczna-inteligencja-zrewolucjonizuje-s.png",
    "sourceTitles":  [
                         "Sztuczna inteligencja może w przyszłości zostać asystentem sędziego? - CIRE.pl",
                         "AI jako asystent sędziego w przyszłości jego samego nigdy nie zastąpi",
                         "Czy sztuczna inteligencja zastąpi sędziów? - Radio Kraków",
                         "Sztuczna inteligencja pomoże sędziom, ale ich nie zastąpi - Legalis",
                         "Wspomaganie sędziów przez sztuczną inteligencję - Instytut Wymiaru Sprawiedliwości",
                         "AI w sądach sprawdzi się jako asystentka, ale sędziego nie zastąpi - Prawo.pl",
                         "Sztuczna inteligencja zastąpi w sądzie protokolanta? - Prawo.pl",
                         "AI umożliwia każdemu złożenie profesjonalnego pozwu. Nowy problem dla wymiaru sprawiedliwości - ITHardware.pl",
                         "Sądownictwo jest skazane na współpracę z AI. Lublin może dać przykład",
                         "Etyka a sztuczna inteligencja – jak daleko możemy posunąć się z poleganiem na AI? Czy AI powinno wydawać wyroki?",
                         "Sztuczna inteligencja już pomaga w postępowaniach przed sądem - GazetaPrawna.pl",
                         "Czy algorytmy zastąpią prawników? - Klub Jagielloński",
                         "Dawid Kulpa: Czy w dobie AI potrzebujemy sędziów przysięgłych? - Prawo.pl",
                         "RAPORT Rekomendacje w zakresie zastosowania sztucznej inteligencji w sądownictwie i prokuraturze - Gov.pl",
                         "Sędzia zagląda w szklaną kulę - Sztuczna Inteligencja",
                         "Zastosowanie sztucznej inteligencji w sądownictwie w świetle zasady skutecznej ochrony sądowej",
                         "Gdy algorytm zmyśla przepisy. Ryzyka AI i granice odpowiedzialności w praktyce prawniczej",
                         "Algorytmy sprawiedliwości. Jak sztuczna inteligencja wpływa na system sądowniczy - Pismo",
                         "Sądownictwo w dobie Sztucznej Inteligencji: czy Temida powinna pozostać ludzka?",
                         "Problematyka prawnej kontroli algorytmów",
                         "Sztuczna inteligencja w prawie karnym - szansa czy ryzyko? - Orlik \u0026amp; Partners",
                         "Sztuczna inteligencja w prawie: jak AI wpływa na systemy prawne i rozstrzyganie sporów cz. II - dotlaw",
                         "O sztucznej inteligencji w wymiarze sprawiedliwości - IWS",
                         "Sztuczna inteligencja w wymiarze sprawiedliwości. Między prawem a algorytmami",
                         "Algorytm jako informacja publiczna w prawie europejskim - Wydawnictwa Uniwersytetu Warszawskiego",
                         "Prawo dostępu do informacji dotyczących zautomatyzowanego podejmowania decyzji wobec zakazu dyskryminacji w prawie europejskim - WPiA UW",
                         "Kontrola prawna nad algorytmami - mec. Krzysztof Izdebski - YouTube"
                     ]
}